gitlab_release_notes/__init__.py
gitlab_release_notes/generate.py
gitlab_release_notes/version.py
gitlab_release_notes-0.2.3.dist-info/licenses/LICENSE
gitlab_release_notes-0.2.3.dist-info/METADATA
gitlab_release_notes-0.2.3.dist-info/WHEEL
gitlab_release_notes-0.2.3.dist-info/entry_points.txt
gitlab_release_notes-0.2.3.dist-info/top_level.txt
gitlab_release_notes-0.2.3.dist-info/RECORD
