Metadata-Version: 2.4
Name: gitlab_release_notes
Version: 0.2.3
Summary: Generate release notes for a gitlab project
Home-page: https://github.com/vuillaut/gitlab_release_notes
Author: vuillaut
License-File: LICENSE
Requires-Dist: python-gitlab>=3.0
Provides-Extra: test
Requires-Dist: pytest; extra == "test"
Dynamic: author
Dynamic: description
Dynamic: description-content-type
Dynamic: home-page
Dynamic: license-file
Dynamic: provides-extra
Dynamic: requires-dist
Dynamic: summary
